split_dataset/__init__.py
split_dataset/select_and_move_images.py
split_dataset/split_dataset.py
split_dataset/split_dataset_s3.py
split_dataset/utils.py
splitdatasets-0.9.0.dist-info/licenses/LICENSE
splitdatasets-0.9.0.dist-info/METADATA
splitdatasets-0.9.0.dist-info/WHEEL
splitdatasets-0.9.0.dist-info/entry_points.txt
splitdatasets-0.9.0.dist-info/top_level.txt
splitdatasets-0.9.0.dist-info/RECORD
