Metadata-Version: 2.4
Name: splitdatasets
Version: 0.9.0
Summary: Tools to randomly move images and split datasets (local or S3) into train/val/test.
Author-email: Daniel Robotics <grabardm@ml-dev.ru>
License-Expression: MIT
Project-URL: Homepage, https://github.com/Daniel-Robotic/SplitDatasets
Project-URL: Source, https://github.com/Daniel-Robotic/SplitDatasets
Project-URL: Tracker, https://github.com/Daniel-Robotic/SplitDatasets/issues
Requires-Python: >=3.12
License-File: LICENSE
Requires-Dist: boto3>=1.39.4
Dynamic: license-file
